{
    "child iterations" : 15, 
    "is fertile" : false, 
    "is classifier" : false, 
    "is child" : false, 
    "weights" : [
        [
            0.805835, 
            0.721707, 
            0.70053, 
            -0.111966, 
            -0.005459, 
            0.570785, 
            0.980641, 
            -0.306229, 
            0.385627, 
            -0.379736, 
            -0.024004, 
            -0.433325, 
            -0.328867, 
            0.38089303082048986, 
            -0.08746, 
            0.893787, 
            1.027903, 
            0.472176, 
            -0.324092, 
            -0.779488, 
            -0.365504, 
            0.52121, 
            0.159726, 
            -0.753882, 
            -0.855209, 
            0.969659, 
            -0.159949, 
            -0.5034832397259552, 
            -0.80204, 
            -0.637212, 
            -0.551357, 
            0.477621, 
            0.518675, 
            -0.888651, 
            -0.026924, 
            0.750827, 
            1.004652, 
            0.218622, 
            0.247236, 
            -0.851095, 
            -0.701375, 
            -0.624458886047381, 
            0.673254, 
            -0.034105, 
            0.471839, 
            -0.699794, 
            -0.531491, 
            0.347336, 
            0.145523, 
            0.023267, 
            0.866488, 
            0.427859, 
            0.977984, 
            0.753647, 
            0.779931, 
            -0.8497572433176033, 
            -0.662883, 
            0.814179, 
            0.04389, 
            -0.513085, 
            -0.004179, 
            0.047937, 
            -0.809438, 
            -0.170054, 
            -0.830153, 
            0.671423, 
            -0.661678, 
            0.008007, 
            -0.779327, 
            -0.2585969399353969, 
            -0.835534, 
            -0.779777, 
            -0.789546, 
            -0.517033, 
            0.360997, 
            -0.120742, 
            -0.069978, 
            0.84616, 
            0.035719, 
            0.242846, 
            -0.855731, 
            -0.592637, 
            0.477764, 
            -0.33040685657431124, 
            0.308002, 
            0.3963, 
            0.905929, 
            -0.826335, 
            0.290929, 
            -0.465042, 
            0.689968, 
            -0.724168, 
            -0.769014, 
            0.989267, 
            1.012919, 
            0.856348, 
            0.829771, 
            -0.6306092805979704, 
            -0.527038, 
            -0.63565, 
            -0.395561, 
            0.333122, 
            -0.464092, 
            0.727817, 
            0.504895, 
            0.152763, 
            -0.440704, 
            1.014999, 
            -0.622855, 
            0.760855, 
            0.439132, 
            0.20435966406008688, 
            0.845633, 
            0.070783, 
            -0.944865, 
            -0.847804, 
            0.447519, 
            0.807963, 
            -0.161511, 
            -0.899221, 
            -1.017696, 
            -0.986653, 
            -0.469553, 
            -0.463755, 
            0.689864, 
            -0.6304343038326945, 
            -0.40493, 
            -0.563317, 
            0.340896, 
            -0.878407, 
            -0.022486, 
            0.016072, 
            -1.030982, 
            0.141597, 
            0.27331, 
            -0.625448, 
            0.427591, 
            -0.451934, 
            0.624961, 
            -0.3046400472593451, 
            -0.861364, 
            0.580538, 
            0.311103, 
            -0.829151, 
            0.913099, 
            -1.028509, 
            0.880982, 
            0.829804, 
            -1.030429, 
            -0.091017, 
            -0.061617, 
            0.191333, 
            0.463963, 
            -0.7946729487057731
        ], 
        [
            0.196692, 
            0.189492, 
            0.16522, 
            -0.166146, 
            0.218012, 
            -0.460915, 
            0.180759, 
            0.075533, 
            -0.392525, 
            -0.305681, 
            0.704991, 
            -0.577602, 
            -0.884291, 
            0.8838087006498039, 
            -0.096369, 
            -0.58447, 
            -0.641543, 
            -0.493635, 
            0.467299, 
            -0.296253, 
            0.338823, 
            0.821769, 
            0.867489, 
            0.940439, 
            0.194191, 
            -0.943206, 
            -0.368347, 
            -0.6607225750493029, 
            -0.54426, 
            -0.075411, 
            -0.834118, 
            0.115041, 
            0.465094, 
            -0.878627, 
            -0.06312, 
            0.01452, 
            0.28004, 
            0.908926, 
            -0.724808, 
            -0.390415, 
            -0.020076, 
            -0.5004723443611248, 
            -0.403489, 
            0.467373, 
            -0.703739, 
            -0.910147, 
            -0.724945, 
            -0.489948, 
            -0.737145, 
            0.359414, 
            -0.949745, 
            -0.802938, 
            -0.472671, 
            -0.20242, 
            0.033966, 
            0.22385523471251112, 
            0.606196, 
            -0.515644, 
            -0.622032, 
            0.502724, 
            -0.247102, 
            0.166649, 
            0.462504, 
            0.597591, 
            -0.23474, 
            0.409078, 
            -0.273447, 
            -0.835011, 
            0.894991, 
            -0.21908172951585092, 
            0.438501, 
            0.170083, 
            -0.245598, 
            0.288252, 
            -0.111036, 
            -0.011208, 
            -0.835777, 
            -0.463841, 
            -0.501713, 
            0.740338, 
            0.776127, 
            -0.002442, 
            -0.332279, 
            0.64061907575733, 
            0.245728, 
            0.732017, 
            0.965589, 
            0.061024, 
            -0.460173, 
            -0.902562, 
            -0.008662, 
            0.165689, 
            -0.04222, 
            -0.634386, 
            0.489362, 
            -0.710678, 
            0.138018, 
            -0.3352827986689313, 
            -0.684425, 
            1.029455, 
            -0.374607, 
            -0.657817, 
            0.905688, 
            0.655492, 
            -0.322539, 
            -0.390169, 
            0.778761, 
            0.582956, 
            -0.346296, 
            -0.625013, 
            -0.635323, 
            -0.26617702080755556, 
            -0.52991, 
            -0.431418, 
            -0.905136, 
            0.138537, 
            0.86085, 
            -0.221318, 
            -0.706275, 
            0.629838, 
            -0.666296, 
            0.851786, 
            -0.455385, 
            -0.899529, 
            0.901276, 
            0.576911501365496, 
            0.165172, 
            0.611795, 
            -0.271482, 
            -0.295038, 
            -0.018972, 
            0.650793, 
            -0.026722, 
            -0.228587, 
            -0.729044, 
            -0.388255, 
            -1.024493, 
            -0.374925, 
            0.532384, 
            -0.44221138173571783, 
            -0.861543, 
            -0.12148, 
            -0.41207, 
            0.27726, 
            0.706144, 
            -0.043357, 
            0.739161, 
            -0.955896, 
            -0.586073, 
            0.939108, 
            0.316632, 
            -0.705886, 
            0.385278, 
            -0.959886400728396, 
            -0.491387, 
            -0.761727, 
            -0.576086, 
            0.686263, 
            -0.716052, 
            0.458339, 
            -0.946798, 
            0.906437, 
            -0.805712, 
            0.496602, 
            0.910758, 
            0.471342, 
            0.347686, 
            -0.16632899504975596, 
            -0.451654, 
            0.856605, 
            -0.365502, 
            -0.070893, 
            0.016341, 
            -0.000733, 
            0.366052, 
            -0.596472, 
            -0.284026, 
            0.517344, 
            0.408651, 
            0.921165, 
            0.149184, 
            -0.3224227194717695, 
            0.760436, 
            -0.203364, 
            -0.934468, 
            -0.030976, 
            -0.145212, 
            0.355506, 
            -0.1247, 
            0.91727, 
            -0.088261, 
            -0.188341, 
            -0.330407, 
            -0.378874, 
            -0.765321, 
            0.6816417842551246
        ], 
        [
            -0.969035, 
            1.040558, 
            -0.621607, 
            0.908903, 
            0.119055, 
            0.472712, 
            -0.619309, 
            -0.209215, 
            -0.474237, 
            -0.435487, 
            -0.979963, 
            0.060916, 
            0.521439, 
            0.686433
        ]
    ], 
    "momentum weights" : [
        [
            0.805835, 
            0.721707, 
            0.70053, 
            -0.111966, 
            -0.005459, 
            0.570785, 
            0.980641, 
            -0.306229, 
            0.385627, 
            -0.379736, 
            -0.024004, 
            -0.433325, 
            -0.328867, 
            0.38089303082048986, 
            -0.08746, 
            0.893787, 
            1.027903, 
            0.472176, 
            -0.324092, 
            -0.779488, 
            -0.365504, 
            0.52121, 
            0.159726, 
            -0.753882, 
            -0.855209, 
            0.969659, 
            -0.159949, 
            -0.5034832397259552, 
            -0.80204, 
            -0.637212, 
            -0.551357, 
            0.477621, 
            0.518675, 
            -0.888651, 
            -0.026924, 
            0.750827, 
            1.004652, 
            0.218622, 
            0.247236, 
            -0.851095, 
            -0.701375, 
            -0.624458886047381, 
            0.673254, 
            -0.034105, 
            0.471839, 
            -0.699794, 
            -0.531491, 
            0.347336, 
            0.145523, 
            0.023267, 
            0.866488, 
            0.427859, 
            0.977984, 
            0.753647, 
            0.779931, 
            -0.8497572433176033, 
            -0.662883, 
            0.814179, 
            0.04389, 
            -0.513085, 
            -0.004179, 
            0.047937, 
            -0.809438, 
            -0.170054, 
            -0.830153, 
            0.671423, 
            -0.661678, 
            0.008007, 
            -0.779327, 
            -0.2585969399353969, 
            -0.835534, 
            -0.779777, 
            -0.789546, 
            -0.517033, 
            0.360997, 
            -0.120742, 
            -0.069978, 
            0.84616, 
            0.035719, 
            0.242846, 
            -0.855731, 
            -0.592637, 
            0.477764, 
            -0.33040685657431124, 
            0.308002, 
            0.3963, 
            0.905929, 
            -0.826335, 
            0.290929, 
            -0.465042, 
            0.689968, 
            -0.724168, 
            -0.769014, 
            0.989267, 
            1.012919, 
            0.856348, 
            0.829771, 
            -0.6306092805979704, 
            -0.527038, 
            -0.63565, 
            -0.395561, 
            0.333122, 
            -0.464092, 
            0.727817, 
            0.504895, 
            0.152763, 
            -0.440704, 
            1.014999, 
            -0.622855, 
            0.760855, 
            0.439132, 
            0.20435966406008688, 
            0.845633, 
            0.070783, 
            -0.944865, 
            -0.847804, 
            0.447519, 
            0.807963, 
            -0.161511, 
            -0.899221, 
            -1.017696, 
            -0.986653, 
            -0.469553, 
            -0.463755, 
            0.689864, 
            -0.6304343038326945, 
            -0.40493, 
            -0.563317, 
            0.340896, 
            -0.878407, 
            -0.022486, 
            0.016072, 
            -1.030982, 
            0.141597, 
            0.27331, 
            -0.625448, 
            0.427591, 
            -0.451934, 
            0.624961, 
            -0.3046400472593451, 
            -0.861364, 
            0.580538, 
            0.311103, 
            -0.829151, 
            0.913099, 
            -1.028509, 
            0.880982, 
            0.829804, 
            -1.030429, 
            -0.091017, 
            -0.061617, 
            0.191333, 
            0.463963, 
            -0.7946729487057731
        ], 
        [
            0.196692, 
            0.189492, 
            0.16522, 
            -0.166146, 
            0.218012, 
            -0.460915, 
            0.180759, 
            0.075533, 
            -0.392525, 
            -0.305681, 
            0.704991, 
            -0.577602, 
            -0.884291, 
            0.8838087006498039, 
            -0.096369, 
            -0.58447, 
            -0.641543, 
            -0.493635, 
            0.467299, 
            -0.296253, 
            0.338823, 
            0.821769, 
            0.867489, 
            0.940439, 
            0.194191, 
            -0.943206, 
            -0.368347, 
            -0.6607225750493029, 
            -0.54426, 
            -0.075411, 
            -0.834118, 
            0.115041, 
            0.465094, 
            -0.878627, 
            -0.06312, 
            0.01452, 
            0.28004, 
            0.908926, 
            -0.724808, 
            -0.390415, 
            -0.020076, 
            -0.5004723443611248, 
            -0.403489, 
            0.467373, 
            -0.703739, 
            -0.910147, 
            -0.724945, 
            -0.489948, 
            -0.737145, 
            0.359414, 
            -0.949745, 
            -0.802938, 
            -0.472671, 
            -0.20242, 
            0.033966, 
            0.22385523471251112, 
            0.606196, 
            -0.515644, 
            -0.622032, 
            0.502724, 
            -0.247102, 
            0.166649, 
            0.462504, 
            0.597591, 
            -0.23474, 
            0.409078, 
            -0.273447, 
            -0.835011, 
            0.894991, 
            -0.21908172951585092, 
            0.438501, 
            0.170083, 
            -0.245598, 
            0.288252, 
            -0.111036, 
            -0.011208, 
            -0.835777, 
            -0.463841, 
            -0.501713, 
            0.740338, 
            0.776127, 
            -0.002442, 
            -0.332279, 
            0.64061907575733, 
            0.245728, 
            0.732017, 
            0.965589, 
            0.061024, 
            -0.460173, 
            -0.902562, 
            -0.008662, 
            0.165689, 
            -0.04222, 
            -0.634386, 
            0.489362, 
            -0.710678, 
            0.138018, 
            -0.3352827986689313, 
            -0.684425, 
            1.029455, 
            -0.374607, 
            -0.657817, 
            0.905688, 
            0.655492, 
            -0.322539, 
            -0.390169, 
            0.778761, 
            0.582956, 
            -0.346296, 
            -0.625013, 
            -0.635323, 
            -0.26617702080755556, 
            -0.52991, 
            -0.431418, 
            -0.905136, 
            0.138537, 
            0.86085, 
            -0.221318, 
            -0.706275, 
            0.629838, 
            -0.666296, 
            0.851786, 
            -0.455385, 
            -0.899529, 
            0.901276, 
            0.576911501365496, 
            0.165172, 
            0.611795, 
            -0.271482, 
            -0.295038, 
            -0.018972, 
            0.650793, 
            -0.026722, 
            -0.228587, 
            -0.729044, 
            -0.388255, 
            -1.024493, 
            -0.374925, 
            0.532384, 
            -0.44221138173571783, 
            -0.861543, 
            -0.12148, 
            -0.41207, 
            0.27726, 
            0.706144, 
            -0.043357, 
            0.739161, 
            -0.955896, 
            -0.586073, 
            0.939108, 
            0.316632, 
            -0.705886, 
            0.385278, 
            -0.959886400728396, 
            -0.491387, 
            -0.761727, 
            -0.576086, 
            0.686263, 
            -0.716052, 
            0.458339, 
            -0.946798, 
            0.906437, 
            -0.805712, 
            0.496602, 
            0.910758, 
            0.471342, 
            0.347686, 
            -0.16632899504975596, 
            -0.451654, 
            0.856605, 
            -0.365502, 
            -0.070893, 
            0.016341, 
            -0.000733, 
            0.366052, 
            -0.596472, 
            -0.284026, 
            0.517344, 
            0.408651, 
            0.921165, 
            0.149184, 
            -0.3224227194717695, 
            0.760436, 
            -0.203364, 
            -0.934468, 
            -0.030976, 
            -0.145212, 
            0.355506, 
            -0.1247, 
            0.91727, 
            -0.088261, 
            -0.188341, 
            -0.330407, 
            -0.378874, 
            -0.765321, 
            0.6816417842551246
        ], 
        [
            -0.969035, 
            1.040558, 
            -0.621607, 
            0.908903, 
            0.119055, 
            0.472712, 
            -0.619309, 
            -0.209215, 
            -0.474237, 
            -0.435487, 
            -0.979963, 
            0.060916, 
            0.521439, 
            0.686433
        ]
    ], 
    "nodes" : [
        [
            -1.0, 
            -0.857142857142864, 
            1.0000000000000073, 
            -0.5743369634849376, 
            -1.0, 
            1.0, 
            1.000000000000009, 
            -0.14066031746032007, 
            1.0, 
            -0.7763578274760393, 
            1.0
        ], 
        [
            -0.8878037761845141, 
            -0.9718740264020848, 
            -0.9965072168889958, 
            -0.8579050398350392, 
            0.9967261030288959, 
            -0.9610830333250012, 
            0.9704773204061992, 
            0.5967940429488798, 
            -0.9714257339984055, 
            0.6775813221099991, 
            0.4509779987398234, 
            -0.8966048358261934, 
            0.9647533068626784, 
            0.7615941559557649
        ], 
        [
            0.9278177247840741, 
            0.9933924564483194, 
            0.9758878699801314, 
            0.2611825894723796, 
            -0.47643562173601767, 
            0.9747987439907511, 
            0.9976716501667476, 
            -0.9708307395797088, 
            0.7544748238335103, 
            -0.9751435889925024, 
            -0.8396706224962616, 
            0.521601690428183, 
            0.7651046031615895, 
            0.7615941559557649
        ], 
        [
            0.9213532129896019
        ]
    ], 
    "pre activation nodes" : [
        [
            0.0, 
            0.0, 
            0.0, 
            0.0, 
            0.0, 
            0.0, 
            0.0, 
            0.0, 
            0.0, 
            0.0, 
            0.0
        ], 
        [
            -1.411460036254852, 
            -2.125023087623524, 
            -3.174227834919837, 
            -1.2853546208025861, 
            3.2066415800761456, 
            -1.9599109253966505, 
            2.100436159622707, 
            0.6881528419258474, 
            -2.117002880097581, 
            0.824628701486212, 
            0.4859272870408901, 
            -1.4546312226725393, 
            2.0103751298451376, 
            1.0
        ], 
        [
            1.6424747047393002, 
            2.854690629769133, 
            2.2030290482681565, 
            0.26737715442070864, 
            -0.5183630494587852, 
            2.1806639677269315, 
            3.3772889079261708, 
            -2.1065474993122413, 
            0.9832626764425874, 
            -2.1876403352405664, 
            -1.2200557582332956, 
            0.5785375668092179, 
            1.0084124688231375, 
            1.0
        ], 
        [
            1.597909119136747
        ]
    ], 
    "average nodes" : [
        [
            0.0, 
            0.0, 
            0.0, 
            0.0, 
            0.0, 
            0.0, 
            0.0, 
            0.0, 
            0.0, 
            0.0, 
            0.0
        ], 
        [
            0.0, 
            0.0, 
            0.0, 
            0.0, 
            0.0, 
            0.0, 
            0.0, 
            0.0, 
            0.0, 
            0.0, 
            0.0, 
            0.0, 
            0.0, 
            0.0
        ], 
        [
            0.0, 
            0.0, 
            0.0, 
            0.0, 
            0.0, 
            0.0, 
            0.0, 
            0.0, 
            0.0, 
            0.0, 
            0.0, 
            0.0, 
            0.0, 
            0.0
        ], 
        [
            0.0
        ]
    ], 
    "input width" : 10, 
    "output width" : 1, 
    "hidden width" : 14, 
    "hidden length" : 2, 
    "hidden layer details" : {
        "items" : 3, 
        "0" : "is shallow", 
        "1" : "probabilities", 
        "2" : "width", 
        "is shallow" : true, 
        "probabilities" : {
            "1" : 0.03, 
            "2" : 0.8, 
            "3" : 0.17
        }, 
        "width" : {
            "no change" : 0.6, 
            "decrease" : 0.35, 
            "increase" : 0.05
        }
    }, 
    "weight range" : 1.0, 
    "activation function" : 2, 
    "learning rate" : 0.05, 
    "momentum active" : true, 
    "momentum" : 0.001, 
    "accuracy requirement" : 0.985, 
    "epochs" : 10, 
    "batch size" : 25, 
    "accuracy sample size" : 150, 
    "fitness sample size" : 15, 
    "allow testing" : false, 
    "show output" : false, 
    "use bias" : true, 
    "clear bias" : false, 
    "bias value" : 1.0, 
    "child" : null
}